{
  "title": "高速な剰余演算",
  "closed": false,
  "archived": false,
  "created_at": "2023-01-11",
  "comments": [
    {
      "author": "mizar",
      "created_at": "2023-01-11",
      "body_markdown": "$a\\times b\\ (\\operatorname{mod}m)$ や $a^r\\ (\\operatorname{mod}m)$ のような計算( $m$ は毎回異なる値ではなく、ある程度は同じ値で $\\operatorname{mod}m$ を行うものとする  )を、なるべく除算を使わずに計算量を抑えるにはどうするか問題。\n\n最適化の方法の例:\n\n- コンパイラ等で用いられる除算最適化（商・剰余の計算、整除性の判定など）\n- Montgomery Reduction\n- Barrett Reduction\n\n何故、汎用の除算命令・除算ルーチンを使う事が避けられるかというと、遅いからである。用途を絞れば、加減乗算や比較などの命令を上手く組み合わせた方が速いケースが多く存在する。",
      "body_updated_at": "2023-01-11"
    },
    {
      "author": "mizar",
      "created_at": "2023-01-11",
      "body_markdown": "# Garnerのアルゴリズム, 中国剰余定理, Montgomery Reduction\n\n## Garnerのアルゴリズム\n\n($\\gcd(M_x,M_y)=1$ の時、 $z\\equiv x\\ (\\operatorname{mod}M_x),\\ z\\equiv y\\ (\\operatorname{mod}M_y)$ が成り立つような 整数 $z$ の値を求めるアルゴリズム)\n\n関連: 中国剰余定理\n\nhttps://ja.wikipedia.org/wiki/%E4%B8%AD%E5%9B%BD%E3%81%AE%E5%89%B0%E4%BD%99%E5%AE%9A%E7%90%86\n\nhttps://qiita.com/drken/items/ae02240cd1f8edfc86fd#2-2-garner-%E3%81%AE%E3%82%A2%E3%83%AB%E3%82%B4%E3%83%AA%E3%82%BA%E3%83%A0\n\n- $x,y\\in\\text{整数}\\mathbb{Z}$\n- $M_x,M_y,\\overline{M_x}\\in\\text{自然数}\\mathbb{N}$\n- $\\gcd(M_x,M_y)=1$\n- $\\overline{M_x}M_x\\equiv 1\\quad(\\operatorname{mod}M_y)$\n- $t=M_x(\\overline{M_x}(x-y)\\operatorname{mod}M_y)$\n- $z=\\begin{cases}x-t&(x \\ge t)\\\\x-t+M_xM_y&(x \\lt t)\\\\\\end{cases}$\n\nとすると\n\n- $0\\le t\\le M_x(M_y-1)$\n- $x-M_x(M_y-1)\\le x-t\\le x+M_xM_y$\n- $z\\equiv x\\quad(\\operatorname{mod}M_x)\\quad\\because\\quad t\\equiv 0\\quad(\\operatorname{mod}M_x)$\n- $z\\equiv y\\quad(\\operatorname{mod}M_y)\\quad\\because\\quad t\\equiv x-y\\quad(\\operatorname{mod}M_y)$\n- 特に、 $0\\le x\\lt M_xM_y$ であれば $0\\le z\\lt M_xM_y$\n\n## Montgomery Reduction\n\n($\\operatorname{mod}2^{64}$ のような、コンピュータが計算しやすい除算に変形させた剰余計算)\n\n上の Garner のアルゴリズムからさらに、\n\n- $\\overline{M_y}\\in\\text{自然数}\\mathbb{N}$\n- $\\overline{M_y}M_y\\equiv 1\\quad(\\operatorname{mod}M_x)$\n- $M_x\\lt M_y$\n- $a,b\\in\\text{整数}\\mathbb{Z}$\n- $a'=M_ya\\operatorname{mod}M_x=\\overline{M_y}((M_y)^2\\operatorname{mod}M_x)a\\operatorname{mod}M_x$\n- $b'=M_yb\\operatorname{mod}M_x=\\overline{M_y}((M_y)^2\\operatorname{mod}M_x)b\\operatorname{mod}M_x$\n- $0\\le x=a'b'\\le (M_x-1)^2$\n- $y=0$\n\nとすると\n\n- $z\\operatorname{mod}M_y=0$\n- $0\\le z/M_y\\lt M_x$\n- $z/M_y=\\overline{M_y}z\\operatorname{mod}M_x=\\overline{M_y}x\\operatorname{mod}M_x$\n- $z/M_y=\\overline{M_y}a'b'\\operatorname{mod}M_x=M_yab\\operatorname{mod}M_x$\n\nこの結果を使うと、 $M_y=2^{64}$ のような、コンピュータにとって除算を計算しやすい数に定めることで\n\n- $M_ya\\times M_yb\\times \\overline{M_y} \\equiv z/M_y\\ (\\operatorname{mod}M_x)$\n\nの形の計算を行うことができる。同じ $\\operatorname{mod}$ での剰余計算の回数が多く、かつ $M_x$ が奇数に限られる場合（偶数の場合の考察は https://www.mathenachia.blog/even-mod-montgomery-impl/ 参照）は Barrett Reduction よりこちらのやり方で剰余計算した方が効率が良い場合がある。\n\nこの式の前提を改めてまとめると以下の通り。\n\n- $\\gcd(M_x,M_y)=1$\n- $M_x\\lt M_y$\n- $\\overline{M_x}M_x\\equiv 1\\quad(\\operatorname{mod}M_y)$\n- $\\overline{M_y}M_y\\equiv 1\\quad(\\operatorname{mod}M_x)$\n- $a'=M_ya\\operatorname{mod}M_x=\\overline{M_y}((M_y)^2\\operatorname{mod}M_x)a\\operatorname{mod}M_x$\n- $b'=M_yb\\operatorname{mod}M_x=\\overline{M_y}((M_y)^2\\operatorname{mod}M_x)b\\operatorname{mod}M_x$\n- $0\\le x=a'b'\\le (M_x-1)^2$\n- $y=0$\n- $t=M_x(\\overline{M_x}(x-y)\\operatorname{mod}M_y)$\n- $z=\\begin{cases}x-t&(x \\ge t)\\\\x-t+M_xM_y&(x \\lt t)\\\\\\end{cases}$\n\nhttps://ja.wikipedia.org/wiki/%E3%83%A2%E3%83%B3%E3%82%B4%E3%83%A1%E3%83%AA%E4%B9%97%E7%AE%97\n\nhttps://www.mathenachia.blog/even-mod-montgomery-impl/\n\nhttps://zenn.dev/mizar/articles/791698ea860581\n\n(C++, モンゴメリリダクション実装例)\n\nhttps://yukicoder.me/submissions/793551\n\n(Rust, モンゴメリリダクション実装例)\n\nhttps://yukicoder.me/submissions/793560\n",
      "body_updated_at": "2023-04-24"
    },
    {
      "author": "mizar",
      "created_at": "2023-01-11",
      "body_markdown": "# Barrett Reduction\n\n- AtCoder Library では汎用的な剰余算のライブラリとして使われている\n- 同じ除数(AtCoder Library の場合は31bit整数までを想定)で剰余算を多く行う場合に有用、 $\\bar{m}' = \\left\\lfloor\\frac{2^{64}-1}{m}\\right\\rfloor+1\\mod2^{64}=\\left\\lceil\\frac{2^{64}}{m}\\right\\rceil\\operatorname{mod}2^{64}$ の値は剰余算を繰り返して行う前に事前計算しておく事を想定\n- 31bit整数 × 31bit整数 $\\operatorname{mod}$ 31bit整数 を計算するために途中で 128bit整数型 が使われている\n  - $ab-qm$ の 符号なし64bit整数同士 ( $ab$ と $qm$ ) の減算部分の繰り下がりチェックを厳格化して $m$ を加算するべきか判定するようにすれば 符号なし32bit整数 × 符号なし32bit整数 $\\operatorname{mod}$ 符号なし32bit整数 に対応可能\n- $\\operatorname{mod}$ 偶数でも計算量は変わらない\n- $\\lfloor x\\rfloor$ は床関数(floor)、 $\\lceil x\\rceil$ は天井関数(ceil)\n\nhttps://ja.wikipedia.org/wiki/%E5%BA%8A%E9%96%A2%E6%95%B0%E3%81%A8%E5%A4%A9%E4%BA%95%E9%96%A2%E6%95%B0\n\nhttps://en.wikipedia.org/wiki/Barrett_reduction\n\n(アルゴリズム)\n\n$$\nm\\in\\text{自然数(natural number)}\\mathbb{N},\\quad 1\\le m\\lt 2^{32}\\\\\n\\lbrace a,b\\rbrace\\in\\text{整数(integer)}\\mathbb{Z},\\quad 0\\le \\lbrace a, b\\rbrace\\lt m\\\\\n\\bar{m}' = \\left\\lfloor\\frac{2^{64}-1}{m}\\right\\rfloor+1\\mod2^{64}=\\left\\lceil\\frac{2^{64}}{m}\\right\\rceil\\operatorname{mod}2^{64}\\\\\nx=\\left\\lfloor\\frac{ab\\hspace{.1em}\\bar{m}'}{2^{64}}\\right\\rfloor\\\\\nab\\operatorname{mod}m=\\begin{cases}ab-xm&(ab\\ge xm)\\\\ ab-xm+m&(ab\\lt xm)\\end{cases}\\\\\n$$\n\n(証明)\n\n1. when $m=1$, $a=b=\\bar{m}'=0$, so okey\n2. when $2\\le m\\lt 2^{32}$,\n    - $2^{32}+2=\\left\\lceil\\frac{2^{64}}{2^{32}-1}\\right\\rceil\\le\\bar{m}'=\\left\\lceil\\frac{2^{64}}{m}\\right\\rceil\\le \\left\\lceil\\frac{2^{64}}{2}\\right\\rceil=2^{63}$\n    - $\\bar{m}'\\hspace{.1em}m=2^{64}+r\\quad(\\lbrace r\\rbrace\\in\\text{整数(integer)}\\mathbb{Z},\\quad 0\\le r\\lt m)$\n    - $z = ab = cm + d\\quad(\\lbrace c,d\\rbrace\\in\\text{整数(integer)}\\mathbb{Z},\\quad 0\\le\\lbrace c,d\\rbrace\\lt m)$\n    - $z\\hspace{.1em}\\bar{m}'=ab\\hspace{.1em}\\bar{m}'=(cm+d)\\hspace{.1em}\\bar{m}'=c(\\bar{m}'\\hspace{.1em}m)+d\\hspace{.1em}\\bar{m}'=2^{64}c+c\\hspace{.1em}r+d\\hspace{.1em}\\bar{m}'$\n    - $2^{64}c\\le ab\\hspace{.1em}\\bar{m}'\\lt 2^{64}(c+2)$\n        - $ab\\hspace{.1em}\\bar{m}'=2^{64}c+c\\hspace{.1em}r+d\\hspace{.1em}\\bar{m}'$\n        - $0\\le c\\hspace{.1em}r\\le (m-1)^2\\le(2^{32}-2)^2=2^{64}-2^{34}+4\\lt 2^{64}$\n        - $0\\le d\\hspace{.1em}\\bar{m}'\\le\\bar{m}'\\hspace{.1em}(m-1)=2^{64}+r-\\bar{m}'\\le 2^{64}+(2^{32}-2)-(2^{32}+2)=2^{64}-4\\lt 2^{64}$\n    - $x=\\left\\lfloor\\frac{ab\\hspace{.1em}\\bar{m}'}{2^{64}}\\right\\rfloor=\\lbrace c$ or $(c+1)\\rbrace$\n    - $ab-xm=ab-\\left\\lfloor\\frac{ab\\hspace{.1em}\\bar{m}'}{2^{64}}\\right\\rfloor m=\\lbrace d$ or $(d-m)\\rbrace$\n\n(元コード)\n\nhttps://github.com/atcoder/ac-library/blob/6c88a70c8f95fef575af354900d107fbd0db1a12/atcoder/internal_math.hpp#L22-L62\n\nhttps://github.com/rust-lang-ja/ac-library-rs/blob/b473a615a7d7cfe4d8b26e369808cb2aa2d2f5a0/src/internal_math.rs#L19-L84\n\n\n(C++: $1\\le m\\lt 2^{32}$ 対応修正案)\n\nhttps://godbolt.org/z/P8749355T\n\n```cpp\n#ifdef _MSC_VER\n#include <intrin.h>\n#endif\n\n// @param a `0 <= a < m`\n// @param b `0 <= b < m`\n// @return `a * b % m`\nunsigned int barrett_mul_before(unsigned int a, unsigned int b, unsigned int _m, unsigned long long im) {\n    // [1] m = 1\n    // a = b = im = 0, so okay\n\n    // [2] m >= 2\n    // im = ceil(2^64 / m)\n    // -> im * m = 2^64 + r (0 <= r < m)\n    // let z = a*b = c*m + d (0 <= c, d < m)\n    // a*b * im = (c*m + d) * im = c*(im*m) + d*im = c*2^64 + c*r + d*im\n    // c*r + d*im < m * m + m * im < m * m + 2^64 + m <= 2^64 + m * (m + 1) < 2^64 * 2\n    // ((ab * im) >> 64) == c or c + 1\n    unsigned long long z = a;\n    z *= b;\n#ifdef _MSC_VER\n    unsigned long long x;\n    _umul128(z, im, &x);\n#else\n    unsigned long long x =\n        (unsigned long long)(((unsigned __int128)(z)*im) >> 64);\n#endif\n    unsigned int v = (unsigned int)(z - x * _m);\n    if (_m <= v) v += _m;\n    return v;\n}\n\n// @param a `0 <= a < m`\n// @param b `0 <= b < m`\n// @return `a * b % m`\nunsigned int barrett_mul_after(unsigned int a, unsigned int b, unsigned int _m, unsigned long long im) {\n    // [1] m = 1\n    // a = b = im = 0, so okay\n\n    // [2] m >= 2\n    // im = ceil(2^64 / m)\n    // -> im * m = 2^64 + r (0 <= r < m)\n    // let z = a*b = c*m + d (0 <= c, d < m)\n    // a*b * im = (c*m + d) * im = c*(im*m) + d*im = c*2^64 + c*r + d*im\n    // c*r + d*im < m * m + m * im < m * m + 2^64 + m <= 2^64 + m * (m + 1) < 2^64 * 2\n    // ((ab * im) >> 64) == c or c + 1\n    unsigned long long z = a;\n    z *= b;\n#ifdef _MSC_VER\n    unsigned long long x;\n    _umul128(z, im, &x);\n#else\n    unsigned long long x =\n        (unsigned long long)(((unsigned __int128)(z)*im) >> 64);\n#endif\n    unsigned long long y = x * _m;\n#ifdef __GNUC__\n    // https://gcc.gnu.org/onlinedocs/gcc/Integer-Overflow-Builtins.html\n    unsigned long long v;\n    unsigned int w = __builtin_usubll_overflow(z, y, &v) ? _m : 0;\n    return (unsigned int)(v + w);\n#elif defined(_MSC_VER) && defined(_M_AMD64)\n    // https://www.intel.com/content/www/us/en/docs/intrinsics-guide/index.html#text=_subborrow_u64&ig_expand=7252\n    unsigned long long v;\n    unsigned int w = _subborrow_u64(0, z, y, &v) ? _m : 0;\n    return (unsigned int)(v + w);\n#else\n    return (unsigned int)((z - y) + (z < y ? _m : 0));\n#endif\n}\n```\n\n(Rust: $1\\le m\\lt 2^{32}$ 対応修正案)\n\nhttps://rust.godbolt.org/z/7P5rjahMn\n\n```rust\n/// Calculates `a * b % m`.\n///\n/// * `a` `0 <= a < m`\n/// * `b` `0 <= b < m`\n/// * `m` `1 <= m <= 2^31`\n/// * `im` = ceil(2^64 / `m`)\n#[allow(clippy::many_single_char_names)]\npub fn mul_mod_before(a: u32, b: u32, m: u32, im: u64) -> u32 {\n    // [1] m = 1\n    // a = b = im = 0, so okay\n\n    // [2] m >= 2\n    // im = ceil(2^64 / m)\n    // -> im * m = 2^64 + r (0 <= r < m)\n    // let z = a*b = c*m + d (0 <= c, d < m)\n    // a*b * im = (c*m + d) * im = c*(im*m) + d*im = c*2^64 + c*r + d*im\n    // c*r + d*im < m * m + m * im < m * m + 2^64 + m <= 2^64 + m * (m + 1) < 2^64 * 2\n    // ((ab * im) >> 64) == c or c + 1\n    let mut z = a as u64;\n    z *= b as u64;\n    let x = (((z as u128) * (im as u128)) >> 64) as u64;\n    let mut v = z.wrapping_sub(x.wrapping_mul(m as u64)) as u32;\n    if m <= v {\n        v = v.wrapping_add(m);\n    }\n    v\n}\n\n/// Calculates `a * b % m`.\n///\n/// * `a` `0 <= a < m`\n/// * `b` `0 <= b < m`\n/// * `m` `1 <= m < 2^32`\n/// * `im` = ceil(2^64 / `m`) = floor((2^64 - 1) / `m`) + 1\n#[allow(clippy::many_single_char_names)]\npub fn mul_mod_after(a: u32, b: u32, m: u32, im: u64) -> u32 {\n    // [1] m = 1\n    // a = b = im = 0, so okay\n\n    // [2] m >= 2\n    // im = ceil(2^64 / m) = floor((2^64 - 1) / m) + 1\n    // -> im * m = 2^64 + r (0 <= r < m)\n    // let z = a*b = c*m + d (0 <= c, d < m)\n    // a*b * im = (c*m + d) * im = c*(im*m) + d*im = c*2^64 + c*r + d*im\n    // c*r + d*im < m * m + m * im < m * m + 2^64 + m <= 2^64 + m * (m + 1) < 2^64 * 2\n    // ((ab * im) >> 64) == c or c + 1\n    let z = (a as u64) * (b as u64);\n    let x = (((z as u128) * (im as u128)) >> 64) as u64;\n    match z.overflowing_sub(x.wrapping_mul(m as u64)) {\n        (v, true) => (v as u32).wrapping_add(m),\n        (v, false) => v as u32,\n    }\n}\n```\n\nhttps://github.com/atcoder/ac-library/issues/149\n\nhttps://github.com/rust-lang-ja/ac-library-rs/issues/111\n",
      "body_updated_at": "2023-01-18"
    },
    {
      "author": "mizar",
      "created_at": "2023-03-27",
      "body_markdown": "## 関数 function\nfn barrett_reduction(z: u64, m: u64, im: u64) -> (u64, u64)\n\n## 出力 output\n\nreturn $(\\lfloor z/m\\rfloor, z\\mod m)$;\n\n## 入力の制約 input constraints\n- $\\left\\{z\\in\\mathbb{Z}\\;\\middle|\\; 0 \\le z \\lt\\max((im-1)\\times m,1)\\right\\}$\n- $\\left\\{m\\in\\mathbb{Z}\\;\\middle|\\; 2 \\le m \\lt 2^{32.5}\\right\\}$\n-  $\\left\\{im\\in\\mathbb{Z}\\;\\middle|\\;  im\\equiv\\left\\lceil 2^{64}/m\\right\\rceil\\mod 2^{64}\\equiv\\left\\lfloor(2^{64}-1)/m\\right\\rfloor +1\\mod 2^{64}\\right\\}$\n\n## アルゴリズム algorithm\n- $v=\\lfloor(z\\times im)/2^{64}\\rfloor$\n- $w=v\\times m$\n- $\\lfloor z/m\\rfloor=\\begin{cases}v&(z\\ge w)\\\\v-1&(z\\lt w)\\end{cases}$\n- $z\\mod m=\\begin{cases}z-w&(z\\ge w)\\\\z-w+m&(z\\lt w)\\end{cases}$\n\n## 実装例 implementation example\n\n```rust\npub fn barrett_reduction(z: u64, m: u64, im: u64) -> (u64, u64) {\n    // return `(floor(z / m), z \\mod m)`\n    // * `z` : `0 <= z < max((im - 1) * m, 1)`\n    // * `m` : `1 <= m < 2^32.5`\n    // * `im = ceil(2^64 / m) mod 2^64 = floor((2^64 - 1) / m) + 1 mod 2^64`\n\n    // [1] m = 1\n    // im = 0, so may fail (must be z = 0 to return correct result)\n\n    // [2] m >= 2\n    // im = ceil(2^64 / m) = floor((2^64 - 1) / m) + 1 >= 2\n    // -> im * m = 2^64 + r (0 <= r < m)\n    // let z = c*m + d (0 <= c < im, 0 <= d < m)\n    // z * im = (c*m + d) * im = c*(im*m) + d*im = c*2^64 + c*r + d*im\n    // c*r + d*im = (c+1)*r - (m-d)*im + 2^64 <= im*(m-2) + 2^64 = 2 * (2^64 - im) < 2 * 2^64\n    // ((z * im) >> 64) == c or c + 1\n\n    debug_assert_eq!(im, ((!0u64) / m).wrapping_add(1));\n    debug_assert!(z < im.saturating_sub(1).saturating_mul(m).max(1));\n    let v = (((z as u128) * (im as u128)) >> 64) as u64;\n    let (t, f) = z.overflowing_sub(v.wrapping_mul(m));\n    (\n        v - (f as u64),\n        t.wrapping_add((f as u64).wrapping_neg() & m),\n    )\n}\n```\n\n## 証明 proof\n\n1. $m=0 \\quad\\to\\quad im:$ 未定義 (Undefined)\n    - ゼロ除算、$im$が制約を満たすことが出来ない\n    - divide by zero, cannot satisfy the $im$ constraint\n\n2. $m=1 \\quad\\to\\quad im=0 \\quad\\to\\quad z=0$\n    - 制約を $0\\le z\\lt 2^{64}$ とすると、 $z\\ne 0$の時、失敗する（$z=0$でないと正しい結果を返さない）\n    - If the constraint is $0\\le z<2^{64}$ then it fails when $z\\ne 0$ (must be $z=0$ to return correct result)\n\n3. $m\\ge 2 \\quad\\to\\quad im=\\lceil 2^{64}/m\\rceil=\\lfloor(2^{64}-1)/m\\rfloor+1$\n    - $0\\le z\\lt(im-1)\\times m=\\lfloor(2^{64}-1)/m\\rfloor\\times m\\le 2^{64}-1\\lt 2^{64}$\n    - $2^{31.5}\\lt im\\le 2^{63}$\n    - $m\\times im=2^{64}+r\\quad\\left\\{r\\in\\mathbb{Z}\\;\\middle|\\; 0\\le r\\lt m\\right\\}$\n    $\\to\\quad r-m\\times im+2^{64}=0$\n    - $z=c\\times m+d\\quad\\left\\{c\\in\\mathbb{Z}\\;\\middle|\\; 0\\le c\\lt im\\right\\},\\left\\{d\\in\\mathbb{Z}\\;\\middle|\\; 0\\le d\\lt m\\right\\}$\n    - $\\left\\{r\\in\\mathbb{Z}\\;\\middle|\\; 0\\le r\\lt m\\right\\}\\quad\\to\\quad r\\le m-1$\n    - $\\left\\{c\\in\\mathbb{Z}\\;\\middle|\\; 0\\le c\\lt im\\right\\}\\quad\\to\\quad c+1\\le im$\n    - $\\left\\{d\\in\\mathbb{Z}\\;\\middle|\\; 0\\le d\\lt m\\right\\}\\quad\\to\\quad d-m\\le -1$\n    - $z\\times im=(c\\times m+d)\\times im=c\\times (m\\times im)+d\\times im=2^{64}\\times c+c\\times r+d\\times im$\n    - $c\\times r+d\\times im=(c\\times r+d\\times im)+(r-m\\times im+2^{64})=(c+1)\\times r+(d-m)\\times im+2^{64}$\n    $\\le im\\times (m-1)+(-1)\\times im+2^{64}=2\\times 2^{64}-2\\times im+m-1$\n    $\\lt 2\\times 2^{64}-2\\times 2^{31.5}+2^{32.5}-1= 2\\times 2^{64}-1\\lt 2\\times 2^{64}$\n    - $2^{64}\\times c\\le z\\times im\\lt 2^{64}\\times(c+2)$\n    - $v=\\lfloor(z\\times im)/2^{64}\\rfloor=c\\text{ or }c+1$\n    - $w=\\lfloor(z\\times im)/2^{64}\\rfloor\\times m\\le\\lfloor z/m\\rfloor\\times m+m$\n    $\\le (im-1)\\times m=\\lfloor(2^{64}-1)/m\\rfloor\\times m\\le 2^{64}-1\\lt 2^{64}$\n"
    },
    {
      "author": "mizar",
      "created_at": "2023-08-02",
      "body_markdown": "(下書き中)\n\n---\n\na. 丁度の値を求める ($d:$ 除数, $x:$ 被除数, $t:$ パラメータ [ $x$ の範囲に影響 ], $r:$ 補助 [ $t,x$ から求まる ])\n\n$\\displaystyle d,r,t,x\\in\\mathbb{Z},\\quad 1\\le d,\\quad 0\\le t,\\quad 0\\leq r=\\left(-2^t\\right)\\operatorname{mod}d\\lt d,\\quad 0\\le rx\\lt 2^t\\displaystyle\\quad\\longrightarrow\\quad\\left\\lfloor\\left\\lceil\\frac{2^t}{d}\\right\\rceil\\times\\frac{x}{2^t}\\right\\rfloor=\\left\\lfloor\\frac{2^t+r}{d}\\times\\frac{x}{2^t}\\right\\rfloor=\\left\\lfloor\\frac{x}{d}+\\frac{rx}{2^t d}\\right\\rfloor=\\left\\lfloor\\frac{x}{d}\\right\\rfloor$\n\n$\\displaystyle x\\in\\mathbb{Z},\\quad 0\\leq x\\lt 2^{67}\\lt\\frac{2^{93}}{39898175}\\quad\\longrightarrow\\quad \\left\\lfloor\\left\\lceil\\frac{2^{93}}{998244353}\\right\\rceil\\times\\frac{x}{2^{93}}\\right\\rfloor=\\left\\lfloor\\frac{2^{93}+39898175}{998244353}\\times\\frac{x}{2^{93}}\\right\\rfloor=\\left\\lfloor\\frac{x}{998244353}\\right\\rfloor$\n\n---\n\nb. 丁度か1小さい値を求める ($d:$ 除数, $x:$ 被除数, $s,t:$ パラメータ [ $x$ の範囲に影響 ])\n\n$\\displaystyle d,s,t,x\\in\\mathbb{Z},\\quad 0\\le s,\\quad 0\\le t,\\quad 2^s\\le d\\le 2^{(s+t)},\\quad\\begin{cases}0\\lt 2^{(s+t)}\\operatorname{mod}d\\lt d,\\quad 0\\le x\\lt \\frac{2^{(s+t)}(d-2^s)}{2^{(s+t)}\\operatorname{mod}d}+2^s\\displaystyle\\quad\\longrightarrow\\quad\\left(\\left\\lfloor\\frac{x}{d}\\right\\rfloor-1\\right)\\le\\left\\lfloor\\left\\lfloor\\frac{x}{2^s}\\right\\rfloor\\left\\lfloor\\frac{2^{(s+t)}}{d}\\right\\rfloor\\frac{1}{2^t}\\right\\rfloor\\le\\left\\lfloor\\frac{x}{d}\\right\\rfloor\\\\2^{(s+t)}\\operatorname{mod}d=0,\\quad 0\\le \\displaystyle\\quad\\longrightarrow\\quad\\left\\lfloor\\left\\lfloor\\frac{x}{2^s}\\right\\rfloor\\left\\lfloor\\frac{2^{(s+t)}}{d}\\right\\rfloor\\frac{1}{2^t}\\right\\rfloor=\\left\\lfloor\\frac{x}{d}\\right\\rfloor\\\\ \\end{cases}$\n\n$\\displaystyle d,s,t,x\\in\\mathbb{Z},\\quad 0\\le s,\\quad 0\\le t,\\quad 2^s\\le d\\le 2^{(s+t)},\\quad 2^{(s+t)}\\not\\equiv 0\\ (\\operatorname{mod}d),\\quad 0\\le x\\lt \\frac{2^{(s+t)}(d-2^s)}{2^{(s+t)}\\operatorname{mod}d}+2^s$\n\n$\\displaystyle\\quad\\longrightarrow\\quad\\left(\\frac{2^s\\left(2^{(s+t)}-\\left(2^{(s+t)}\\operatorname{mod}d\\right)\\right)}{2^{(s+t)}d}-1\\right)\\lt\\left(-\\frac{2^{(s+t)}\\operatorname{mod}d}{2^{(s+t)}d}x\\right)\\leq 0 \\quad\\quad$ $\\displaystyle\\left(-\\frac{2^{(s+t)}\\operatorname{mod}d}{2^{(s+t)}d}\\text{ を掛ける}\\right)$\n\n$\\displaystyle\\quad\\longrightarrow\\quad\\left(\\frac{x}{d}-1\\right)\\lt\\frac{\\left(x-2^s\\right)\\left(2^{(s+t)}-\\left(2^{(s+t)}\\operatorname{mod}d\\right)\\right)}{2^{(s+t)}d}=\\left(\\frac{x-2^s}{2^s}\\left\\lfloor\\frac{2^{(s+t)}}{d}\\right\\rfloor\\frac{1}{2^t}\\right)\\leq\\left(\\frac{x}{d}-\\frac{1}{2^t}\\left\\lfloor\\frac{2^{(s+t)}}{d}\\right\\rfloor\\right)\\lt\\frac{x}{d}\\quad\\quad$ $\\displaystyle\\left(\\left(\\frac{x}{d}-\\frac{1}{2^t}\\left\\lfloor\\frac{2^{(s+t)}}{d}\\right\\rfloor\\right)=\\frac{2^{(s+t)}x-2^s\\left(2^{(s+t)}-\\left(2^{(s+t)}\\operatorname{mod}d\\right)\\right)}{2^{(s+t)}d}\\text{ を足す},\\ \\frac{2^{(s+t)}-\\left(2^{(s+t)}\\operatorname{mod}d\\right)}{d}=\\left\\lfloor\\frac{2^{(s+t)}}{d}\\right\\rfloor\\right)$\n\n$\\displaystyle\\quad\\longrightarrow\\quad \\left(\\frac{x}{d}-1\\right)\\lt\\left(\\frac{x-2^s}{2^s}\\left\\lfloor\\frac{2^{(s+t)}}{d}\\right\\rfloor\\frac{1}{2^t}\\right)\\lt\\left(\\left\\lfloor\\frac{x}{2^s}\\right\\rfloor\\left\\lfloor\\frac{2^{(s+t)}}{d}\\right\\rfloor\\frac{1}{2^t}\\right)\\le\\frac{x}{d}\\quad\\quad$ $\\displaystyle\\left(\\frac{x}{2^s}-1=\\frac{x-2^s}{2^s}\\lt\\left\\lfloor\\frac{x}{2^s}\\right\\rfloor\\le\\frac{x}{2^s}\\right)$\n\n$\\displaystyle\\quad\\longrightarrow\\quad\\left(\\left\\lfloor\\frac{x}{d}\\right\\rfloor-1\\right)\\le\\left\\lfloor\\left\\lfloor\\frac{x}{2^s}\\right\\rfloor\\left\\lfloor\\frac{2^{(s+t)}}{d}\\right\\rfloor\\frac{1}{2^t}\\right\\rfloor\\le\\left\\lfloor\\frac{x}{d}\\right\\rfloor\\quad\\quad$ $\\left(\\text{床関数(floor)を適用}\\right)$\n\n$\\displaystyle x\\in\\mathbb{Z},\\quad 0\\leq x\\lt 2^{64}\\lt\\frac{2^{64}\\times(998244353-1)}{2^{64}\\operatorname{mod}998244353}+1\\quad\\longrightarrow\\quad\\left\\lfloor\\frac{x}{998244353}\\right\\rfloor-1\\leq\\left\\lfloor\\left\\lfloor\\frac{2^{64}}{998244353}\\right\\rfloor\\times\\frac{x}{2^{64}}\\right\\rfloor\\leq\\left\\lfloor\\frac{x}{998244353}\\right\\rfloor$\n\n---\n\nc. 丁度か1大きい値を求める ($d:$ 除数, $x:$ 被除数, $s,t:$ パラメータ [ $x$ の範囲に影響 ])\n\n$\\displaystyle d,s,t,x\\in\\mathbb{Z},\\quad 0\\le s,\\quad 0\\le t,\\quad 2^s\\le d\\le 2^{(s+t)},\\quad\\begin{cases}0\\lt\\left(-2^{(s+t)}\\right)\\operatorname{mod}d\\lt d,\\quad 0\\le x\\lt \\frac{2^{(s+t)}(d-2^s)}{\\left(-2^{(s+t)}\\right)\\operatorname{mod}d}-2^s\\displaystyle\\quad\\longrightarrow\\quad\\left\\lfloor\\frac{x}{d}\\right\\rfloor\\le\\left\\lfloor\\left\\lceil\\frac{x}{2^s}\\right\\rceil\\left\\lceil\\frac{2^{(s+t)}}{d}\\right\\rceil\\frac{1}{2^t}\\right\\rfloor\\le\\left(\\left\\lfloor\\frac{x}{d}\\right\\rfloor+1\\right)\\\\\\left(-2^{(s+t)}\\right)\\operatorname{mod}d=0,\\quad 0\\le x\\displaystyle\\quad\\longrightarrow\\quad\\left\\lfloor\\frac{x}{d}\\right\\rfloor\\le\\left\\lfloor\\left\\lceil\\frac{x}{2^s}\\right\\rceil\\left\\lceil\\frac{2^{(s+t)}}{d}\\right\\rceil\\frac{1}{2^t}\\right\\rfloor\\le\\left(\\left\\lfloor\\frac{x}{d}\\right\\rfloor+1\\right)\\\\\\end{cases}$\n\n$\\displaystyle d,s,t,x\\in\\mathbb{Z},\\quad 0\\le s,\\quad 0\\le t,\\quad 2^s\\le d\\le 2^{(s+t)},\\quad 2^{(s+t)}\\not\\equiv 0\\ (\\operatorname{mod}d),\\quad 0\\le x\\lt \\frac{2^{(s+t)}(d-2^s+1)}{\\left(-2^{(s+t)}\\right)\\operatorname{mod}d}-2^s+1$\n\n$\\displaystyle\\quad\\longrightarrow\\quad 0\\leq \\frac{\\left(-2^{(s+t)}\\right)\\operatorname{mod}d}{2^{(s+t)}d}x\\lt \\left(1-\\frac{(2^s-1)\\left(2^{(s+t)}+\\left(\\left(-2^{(s+t)}\\right)\\operatorname{mod}d\\right)\\right)}{2^{(s+t)}d}\\right) \\quad\\quad$ $\\displaystyle\\left(\\frac{\\left(-2^{(s+t)}\\right)\\operatorname{mod}d}{2^{(s+t)}d}\\text{ を掛ける}\\right)$\n\n$\\displaystyle\\quad\\longrightarrow\\quad\\frac{x}{d}\\lt\\left(\\frac{x}{d}+\\frac{2^s-1}{2^{(s+t)}}\\left\\lceil\\frac{2^{(s+t)}}{d}\\right\\rceil\\right)\\leq \\frac{\\left(x+2^s\\right)\\left(2^{(s+t)}+\\left(\\left(-2^{(s+t)}\\right)\\operatorname{mod}d\\right)\\right)}{2^{(s+t)}d}=\\left(\\frac{x+2^s}{2^s}\\left\\lceil\\frac{2^{(s+t)}}{d}\\right\\rceil\\frac{1}{2^t}\\right)\\lt\\left(\\frac{x}{d}+1\\right)$\n$\\displaystyle\\left(\\left(\\frac{x}{d}+\\frac{2^s-1}{2^{(s+t)}}\\left\\lceil\\frac{2^{(s+t)}}{d}\\right\\rceil\\right)=\\frac{2^{(s+t)}x+(2^s-1)\\left(2^{(s+t)}+\\left(\\left(-2^{(s+t)}\\right)\\operatorname{mod}d\\right)\\right)}{2^{(s+t)}d}\\text{ を足す},\\ \\frac{2^{(s+t)}+\\left(\\left(-2^{(s+t)}\\right)\\operatorname{mod}d\\right)}{d}=\\left\\lceil\\frac{2^{(s+t)}}{d}\\right\\rceil\\right)$\n\n$\\displaystyle\\quad\\longrightarrow\\quad\\frac{x}{d}\\leq\\left(\\left\\lceil\\frac{x}{2^s}\\right\\rceil\\left\\lceil\\frac{2^{(s+t)}}{d}\\right\\rceil\\frac{1}{2^t}\\right)\\leq\\left(\\frac{x+2^s-1}{2^s}\\left\\lceil\\frac{2^{(s+t)}}{d}\\right\\rceil\\frac{1}{2^t}\\right)\\lt\\left(\\frac{x}{d}+1\\right)\\quad\\quad$ $\\displaystyle\\left(\\frac{x}{2^s}\\leq\\left\\lceil\\frac{x}{2^s}\\right\\rceil\\leq\\frac{x+2^s-1}{2^s}\\lt\\frac{x}{2^s}+1\\right)$\n\n$\\displaystyle\\quad\\longrightarrow\\quad\\left\\lfloor\\frac{x}{d}\\right\\rfloor\\le\\left\\lfloor\\left\\lceil\\frac{x}{2^s}\\right\\rceil\\left\\lceil\\frac{2^{(s+t)}}{d}\\right\\rceil\\frac{1}{2^t}\\right\\rfloor\\le\\left(\\left\\lfloor\\frac{x}{d}\\right\\rfloor+1\\right)\\quad\\quad$ $\\left(\\text{床関数(floor)を適用}\\right)$\n\n$\\displaystyle x\\in\\mathbb{Z},\\quad 0\\leq x\\lt 2^{67}\\lt\\frac{2^{64}\\times(998244353-1)}{(-2^{64})\\operatorname{mod}998244353}-1\\quad\\longrightarrow\\quad\\left\\lfloor\\frac{x}{998244353}\\right\\rfloor\\leq\\left\\lfloor\\left\\lceil\\frac{2^{64}}{998244353}\\right\\rceil\\times\\frac{x}{2^{64}}\\right\\rfloor\\leq\\left\\lfloor\\frac{x}{998244353}\\right\\rfloor+1$\n\n---\n",
      "body_updated_at": "2023-08-02"
    },
    {
      "author": "mizar",
      "created_at": "2023-08-07",
      "body_markdown": "(下書き中)\n\na. 丁度の値を求める ($d:$ 除数, $x:$ 被除数, $W:$ 整数型のbit長)\n\n$W,d,x\\in\\mathbb{Z},\\quad 2\\leq W,\\quad 1\\leq d\\lt 2^W,\\quad 0\\leq x\\lt 2^W$ において 除算の商 $\\left\\lfloor x/d\\right\\rfloor$ を計算:\n\n`mulh(m, x)` $\\displaystyle=\\left\\lfloor\\frac{mx}{2^W}\\right\\rfloor\\quad\\left(m,x\\in\\mathbb{Z},\\quad 0\\le m\\lt 2^W,\\quad 0\\le x\\lt 2^W\\right)$\n\n- $d=1$ の場合:\n    - $\\displaystyle\\left\\lfloor\\frac{x}{d}\\right\\rfloor=x$\n    - 擬似コード: `x`\n- $\\log_2d=\\lceil\\log_2d\\rceil$ ($d$ が $2$ の累乗数) の場合:\n    - $\\displaystyle t=\\log_2d,\\quad\\left\\lfloor\\frac{x}{d}\\right\\rfloor=\\left\\lfloor\\frac{x}{2^{\\log_2d}}\\right\\rfloor$\n    - 前計算: $s=\\log_2d$\n    - 擬似コード: `x >> s`\n- $\\displaystyle\\log_2d\\ne\\lceil\\log_2d\\rceil,\\quad t=\\lfloor\\log_2((2^W-1)d)\\rfloor,\\quad\\left(-2^t\\right)\\operatorname{mod}d\\lt 2^{(t-W)}$ の場合:\n    - $\\displaystyle t=\\lfloor\\log_2((2^W-1)d)\\rfloor,\\quad\\left\\lfloor\\frac{x}{d}\\right\\rfloor=\\left\\lfloor\\left\\lceil\\frac{2^t}{d}\\right\\rceil\\frac{x}{2^t}\\right\\rfloor=\\left\\lfloor\\left\\lfloor\\left\\lceil\\frac{2^t}{d}\\right\\rceil\\frac{x}{2^W}\\right\\rfloor\\frac{1}{2^{(t-W)}}\\right\\rfloor$\n    - 前計算: $\\displaystyle t=\\lfloor\\log_2((2^W-1)d)\\rfloor,\\quad s=t-W,\\quad m=\\left\\lceil\\frac{2^t}{d}\\right\\rceil$\n    - 擬似コード: `mulh(m, x) >> s`\n- 上記以外の場合:\n    - $\\displaystyle t=W+\\lceil\\log_2d\\rceil,\\quad y=\\left\\lfloor\\left(\\left\\lceil\\frac{2^t}{d}\\right\\rceil-2^W\\right)\\frac{x}{2^W}\\right\\rfloor,$\n      $\\displaystyle\\left\\lfloor\\frac{x}{d}\\right\\rfloor=\\left\\lfloor\\left\\lceil\\frac{2^t}{d}\\right\\rceil\\frac{x}{2^t}\\right\\rfloor=\\left\\lfloor\\left(\\left\\lfloor\\frac{x-y}{2}\\right\\rfloor+y\\right)\\frac{1}{2^{(t-W-1)}}\\right\\rfloor$\n    - 前計算: $\\displaystyle t=W+\\lceil\\log_2d\\rceil,\\quad s=t-W-1,\\quad m=\\left\\lceil\\frac{2^t}{d}\\right\\rceil-2^W$\n    - 擬似コード: `y = mulh(m, x); (((x - y) >> 1) + y) >> s`\n\n---\n\nb. 丁度か $1$ 小さい値を求める ($d:$ 除数, $x:$ 被除数, $s,t:$ パラメータ [ $x$ の範囲に影響 ])\n\n$\\displaystyle d,s,t,x\\in\\mathbb{Z},\\quad 0\\le s,\\quad 0\\le t,\\quad 2^s\\le d\\le 2^{(s+t)},$\n\n$\\begin{cases}\\displaystyle\\left(\\left\\lfloor\\frac{x}{d}\\right\\rfloor-1\\right)\\le\\left\\lfloor\\left\\lfloor\\frac{x}{2^s}\\right\\rfloor\\left\\lfloor\\frac{2^{(s+t)}}{d}\\right\\rfloor\\frac{1}{2^t}\\right\\rfloor\\le\\left\\lfloor\\frac{x}{d}\\right\\rfloor\\\\ \\quad\\quad\\displaystyle\\left(0\\lt 2^{(s+t)}\\operatorname{mod}d\\lt d,\\quad 0\\le x\\lt \\frac{2^{(s+t)}(d-2^s+1)}{2^{(s+t)}\\operatorname{mod}d}+2^s-1\\right)\\\\\\displaystyle\\left\\lfloor\\frac{x}{d}\\right\\rfloor=\\left\\lfloor\\left\\lfloor\\frac{x}{2^s}\\right\\rfloor\\left\\lfloor\\frac{2^{(s+t)}}{d}\\right\\rfloor\\frac{1}{2^t}\\right\\rfloor\\\\ \\quad\\quad\\displaystyle\\left(2^{(s+t)}\\operatorname{mod}d=0,\\quad 0\\le x\\displaystyle\\right)\\end{cases}$\n\n前計算: $\\displaystyle m=\\left\\lfloor\\frac{2^{(s+t)}}{d}\\right\\rfloor$\n\n擬似コード: `((x >> s) * m) >> t`\n\n$s=0$ の場合の擬似コード: `(x * m) >> t`\n\n---\n\nc. 丁度か $1$ 大きい値を求める ($d:$ 除数, $x:$ 被除数, $s,t:$ パラメータ [ $x$ の範囲に影響 ])\n\n$\\displaystyle d,s,t,x\\in\\mathbb{Z},\\quad 0\\le s,\\quad 0\\le t,\\quad 2^s\\le d\\le 2^{(s+t)},$\n\n$\\begin{cases}\\displaystyle\\left\\lfloor\\frac{x}{d}\\right\\rfloor\\le\\left\\lfloor\\left\\lceil\\frac{x}{2^s}\\right\\rceil\\left\\lceil\\frac{2^{(s+t)}}{d}\\right\\rceil\\frac{1}{2^t}\\right\\rfloor\\le\\left(\\left\\lfloor\\frac{x}{d}\\right\\rfloor+1\\right)\\\\ \\quad\\quad\\displaystyle\\left(0\\lt\\left(-2^{(s+t)}\\right)\\operatorname{mod}d\\lt d,\\quad 0\\le x\\lt \\frac{2^{(s+t)}(d-2^s+1)}{\\left(-2^{(s+t)}\\right)\\operatorname{mod}d}-2^s+1\\right)\\\\ \\displaystyle\\left\\lfloor\\frac{x}{d}\\right\\rfloor\\le\\left\\lfloor\\left\\lceil\\frac{x}{2^s}\\right\\rceil\\left\\lceil\\frac{2^{(s+t)}}{d}\\right\\rceil\\frac{1}{2^t}\\right\\rfloor\\le\\left(\\left\\lfloor\\frac{x}{d}\\right\\rfloor+1\\right)\\\\ \\quad\\quad\\displaystyle\\left(\\left(-2^{(s+t)}\\right)\\operatorname{mod}d=0,\\quad 0\\le x\\right)\\end{cases}$\n\n前計算: $\\displaystyle u=2^s-1,\\quad m=\\left\\lceil\\frac{2^{(s+t)}}{d}\\right\\rceil$\n\n擬似コード: `(((x + u) >> s) * m) >> t`\n\n$s=0$ の場合の擬似コード: `(x * m) >> t`\n\n$s=0$ の場合のみの実用を想定。 ($s\\gt 0$ だと b. の手法に比べて利点が薄いため)\n\n---\n\n`(a * b) >> 64`, `x / 998244353`, `x mod 998244353`, `x / 7`, `x mod 7` を計算する関数とそのコンパイル結果の例 (C++): https://godbolt.org/z/6fbWGsEhr\n```cpp\n#include <cstdint>\n#ifdef _MSC_VER\n#include <intrin.h>\n#endif\n// u64mulh_shim(a, b) == floor(a * b / 2**64)\nuint64_t u64mulh_shim(uint64_t a, uint64_t b) {\n#ifdef _MSC_VER // msvc https://learn.microsoft.com/ja-jp/cpp/intrinsics/umulh?view=msvc-170\n    return __umulh(a, b);\n#else // gcc/clang \n    return (unsigned __int128)a * (unsigned __int128)b >> 64;\n#endif\n}\n// div998244353_shim(x) == floor(x / 998244353)\nuint64_t div998244353_shim(uint64_t x) {\n    // 0 <= x < (2**93 / ((-2**93) mod 998244353)) --> floor(ceil(2**93 / 998244353) * x / 2**93) == floor(x / 998244353)\n    // ceil(2**93 / 998244353) == floor((2**93 - 1) / 998244353) + 1 == 9920937979283557439\n    // floor(x / 998244353) == floor((x * 9920937979283557439) / 2**93) == floor(floor((x * 9920937979283557439) / 2**64) / 2**29)\n    return u64mulh_shim(x, 9920937979283557439ULL) >> 29;\n}\nuint64_t div998244353(uint64_t x) {\n    return x / 998244353ULL;\n}\n// rem998244353_shim(x) == (x mod 998244353)\nuint64_t rem998244353_shim(uint64_t x) {\n    return x - div998244353_shim(x) * 998244353ULL;\n}\nuint64_t rem998244353(uint64_t x) {\n    return x % 998244353ULL;\n}\n// div7_shim(x) == floor(x / 7)\nuint64_t div7_shim(uint64_t x) {\n    // 0 <= x < (2**67 / ((-2**67) mod 7)) --> floor(ceil(2**67 / 7) * x / 2**67) == floor(x / 7)\n    // y := floor((ceil(2**67 / 7) - 2**64) * x / 2**64)\n    // floor(x / 7) == floor((x + y) / 2**3) == floor((floor((x - y) / 2) + y) / 2**2)\n    // ceil(2**67 / 7) - 2**64 == 2635249153387078803\n    uint64_t y = u64mulh_shim(x, 2635249153387078803ULL);\n    return (((x - y) >> 1) + y) >> 2;\n}\nuint64_t div7(uint64_t x) {\n    return x / 7;\n}\n// rem7_shim(x) == (x mod 7)\nuint64_t rem7_shim(uint64_t x) {\n    return x - div7_shim(x) * 7ULL;\n}\nuint64_t rem7(uint64_t x) {\n    return x % 7ULL;\n}\n```\n\n```nasm\n# x86-64 gcc\nu64mulh_shim(unsigned long, unsigned long):\n    mov     rax, rdi\n    mul     rsi\n    mov     rax, rdx\n    ret\ndiv998244353_shim(unsigned long):\n    movabs  rax, -8525806094425994177\n    mul     rdi\n    mov     rax, rdx\n    shr     rax, 29\n    ret\ndiv998244353(unsigned long):\n    movabs  rax, -8525806094425994177\n    mul     rdi\n    mov     rax, rdx\n    shr     rax, 29\n    ret\nrem998244353_shim(unsigned long):\n    movabs  rax, -8525806094425994177\n    mul     rdi\n    mov     rax, rdi\n    shr     rdx, 29\n    imul    rdx, rdx, 998244353\n    sub     rax, rdx\n    ret\nrem998244353(unsigned long):\n    movabs  rax, -8525806094425994177\n    mul     rdi\n    mov     rax, rdx\n    shr     rax, 29\n    imul    rdx, rax, 998244353\n    mov     rax, rdi\n    sub     rax, rdx\n    ret\ndiv7_shim(unsigned long):\n    movabs  rax, 2635249153387078803\n    mul     rdi\n    sub     rdi, rdx\n    shr     rdi\n    lea     rax, [rdi+rdx]\n    shr     rax, 2\n    ret\ndiv7(unsigned long):\n    movabs  rax, 2635249153387078803\n    mul     rdi\n    sub     rdi, rdx\n    shr     rdi\n    lea     rax, [rdx+rdi]\n    shr     rax, 2\n    ret\nrem7_shim(unsigned long):\n    movabs  rax, 2635249153387078803\n    mov     rcx, rdi\n    mul     rdi\n    mov     rax, rdi\n    sub     rcx, rdx\n    shr     rcx\n    add     rdx, rcx\n    shr     rdx, 2\n    lea     rcx, [0+rdx*8]\n    sub     rcx, rdx\n    sub     rax, rcx\n    ret\nrem7(unsigned long):\n    movabs  rax, 2635249153387078803\n    mul     rdi\n    mov     rax, rdi\n    sub     rax, rdx\n    shr     rax\n    add     rax, rdx\n    shr     rax, 2\n    lea     rdx, [0+rax*8]\n    sub     rdx, rax\n    mov     rax, rdi\n    sub     rax, rdx\n    ret\n```\n\n```nasm\n# ARM64 gcc\nu64mulh_shim(unsigned long, unsigned long):\n    umulh   x0, x0, x1\n    ret\ndiv998244353_shim(unsigned long):\n    mov     x1, 52287\n    movk    x1, 0x5de0, lsl 16\n    movk    x1, 0x4087, lsl 32\n    movk    x1, 0x89ae, lsl 48\n    umulh   x0, x0, x1\n    lsr     x0, x0, 29\n    ret\ndiv998244353(unsigned long):\n    mov     x1, 52287\n    movk    x1, 0x5de0, lsl 16\n    movk    x1, 0x4087, lsl 32\n    movk    x1, 0x89ae, lsl 48\n    umulh   x0, x0, x1\n    lsr     x0, x0, 29\n    ret\nrem998244353_shim(unsigned long):\n    mov     x2, 52287\n    movk    x2, 0x5de0, lsl 16\n    movk    x2, 0x4087, lsl 32\n    movk    x2, 0x89ae, lsl 48\n    umulh   x2, x0, x2\n    lsr     x2, x2, 29\n    lsl     x1, x2, 4\n    sub     x1, x1, x2\n    lsl     x1, x1, 3\n    sub     x1, x1, x2\n    add     x1, x2, x1, lsl 23\n    sub     x0, x0, x1\n    ret\nrem998244353(unsigned long):\n    mov     x2, 52287\n    movk    x2, 0x5de0, lsl 16\n    movk    x2, 0x4087, lsl 32\n    movk    x2, 0x89ae, lsl 48\n    umulh   x2, x0, x2\n    lsr     x2, x2, 29\n    lsl     x1, x2, 4\n    sub     x1, x1, x2\n    lsl     x1, x1, 3\n    sub     x1, x1, x2\n    add     x1, x2, x1, lsl 23\n    sub     x0, x0, x1\n    ret\ndiv7_shim(unsigned long):\n    mov     x1, 9363\n    movk    x1, 0x9249, lsl 16\n    movk    x1, 0x4924, lsl 32\n    movk    x1, 0x2492, lsl 48\n    umulh   x1, x0, x1\n    sub     x0, x0, x1\n    add     x0, x1, x0, lsr 1\n    lsr     x0, x0, 2\n    ret\ndiv7(unsigned long):\n    mov     x1, 9363\n    movk    x1, 0x9249, lsl 16\n    movk    x1, 0x4924, lsl 32\n    movk    x1, 0x2492, lsl 48\n    umulh   x1, x0, x1\n    sub     x0, x0, x1\n    add     x0, x1, x0, lsr 1\n    lsr     x0, x0, 2\n    ret\nrem7_shim(unsigned long):\n    mov     x2, 9363\n    movk    x2, 0x9249, lsl 16\n    movk    x2, 0x4924, lsl 32\n    movk    x2, 0x2492, lsl 48\n    umulh   x2, x0, x2\n    sub     x1, x0, x2\n    add     x1, x2, x1, lsr 1\n    lsr     x1, x1, 2\n    lsl     x2, x1, 3\n    sub     x1, x2, x1\n    sub     x0, x0, x1\n    ret\nrem7(unsigned long):\n    mov     x2, 9363\n    movk    x2, 0x9249, lsl 16\n    movk    x2, 0x4924, lsl 32\n    movk    x2, 0x2492, lsl 48\n    umulh   x2, x0, x2\n    sub     x1, x0, x2\n    add     x1, x2, x1, lsr 1\n    lsr     x1, x1, 2\n    lsl     x2, x1, 3\n    sub     x1, x2, x1\n    sub     x0, x0, x1\n    ret\n```\n",
      "body_updated_at": "2023-08-07"
    },
    {
      "author": "mizar",
      "created_at": "2023-08-08",
      "body_markdown": "http://web.archive.org/web/20211009144445/https://min-25.hatenablog.com/entry/2017/08/20/171214"
    },
    {
      "author": "mizar",
      "created_at": "2023-08-09",
      "body_markdown": "(下書き中)\n\n## 除算の商を求める3つのアプローチ\n\nこの節では、除算の商 $\\lfloor x/d\\rfloor$ を求めるアプローチを3つ考えてみます。\n\n- a. 丁度の値を求める\n    - $\\lfloor x/d\\rfloor=f_d(x)$\n- b. 丁度か $1$ 小さい値を求める\n    - $\\lfloor x/d\\rfloor-1\\leq f_d(x)\\leq\\lfloor x/d\\rfloor$\n- c. 丁度か $1$ 大きい値を求める\n    - $\\lfloor x/d\\rfloor\\leq f_d(x)\\leq\\lfloor x/d\\rfloor+1$\n\nコンパイラによる最適化で使われるパターンは主に 「a. 丁度の値を求める」 ですが、\n\n後者の2つのアプローチは、求めた除算の商の近似値から、仮に除算の剰余を計算してみて、商が大きすぎたり小さすぎたりしたと分かれば商の近似値から1だけ調整して、正しい除算の商とするものです。後ほど、 「b. 丁度か $1$ 小さい値を求める」 パターンで 被除数 $0\\leq x\\lt 2^{128}$ に対して 除数 $d=10^{32}$ での除算最適化を行う例を紹介します。\n\nまた、以下のような略記を所々で使うので定義しておきます。\n\n- `mulh(m, x)` $\\displaystyle=\\left\\lfloor\\frac{mx}{2^W}\\right\\rfloor\\quad\\left(m,x\\in\\mathbb{Z},\\quad 0\\le m\\lt 2^W,\\quad 0\\le x\\lt 2^W\\right)$\n    - $W$ ビット整数どうしの乗算の積の、上位 $W$ ビットを取り出す関数。（主に $W=64$）\n- $\\displaystyle\\left(-2^t\\right)\\operatorname{mod}d=(d-1)-\\left(\\left(2^t-1\\right)\\operatorname{mod}d\\right)\\quad\\left(d,t\\in\\mathbb{Z},\\quad 1\\leq d\\lt 2^W,\\quad 0\\leq t\\right)$\n    - 負の被除数に対する剰余計算。ここでは主に、「$((2^t\\text{ 以上で }d\\text{ の倍数となる最小の整数}) - 2^t)$ はいくつ?」という文脈で使います。\n    - 逆に、「$(2^t-(2^t\\text{ 以下で }d\\text{ の倍数となる最大の整数}))$ はいくつ?」という文脈では、 $2^t\\operatorname{mod}d$ のように表記します。\n\n### a. 丁度の値を求める ($d:$ 除数, $x:$ 被除数, $W:$ 整数型のbit長)\n\n$\\displaystyle d,r,t,x\\in\\mathbb{Z},\\quad 1\\leq d,\\quad 0\\leq t,\\quad 0\\leq r=\\left(-2^t\\right)\\operatorname{mod}d\\lt d,\\quad 0\\le rx\\lt 2^t$\n\n$\\displaystyle\\quad\\longrightarrow\\quad\\left\\lfloor\\left\\lceil\\frac{2^t}{d}\\right\\rceil\\times\\frac{x}{2^t}\\right\\rfloor=\\left\\lfloor\\frac{2^t+r}{d}\\times\\frac{x}{2^t}\\right\\rfloor=\\left\\lfloor\\frac{x}{d}+\\frac{rx}{2^t d}\\right\\rfloor=\\left\\lfloor\\frac{x}{d}\\right\\rfloor$\n\n$2^t$ 以上で最小の $d$ の倍数を $(2^t+r)$ として、仮に $0\\leq rx\\lt 2^t$ だったとすると、 $\\displaystyle 0\\leq\\frac{rx}{2^t}\\lt 1,\\quad 0\\leq\\frac{rx}{2^td}\\lt\\frac{1}{d}$ が導かれることから、 $\\displaystyle\\left\\lfloor\\left\\lceil\\frac{2^t}{d}\\right\\rceil\\times\\frac{x}{2^t}\\right\\rfloor=\\left\\lfloor\\frac{x}{d}\\right\\rfloor$ となります。\n\n#### $2^W$ 未満の整数を扱う場合の例\n\n$W,d,x\\in\\mathbb{Z},\\quad 2\\leq W,\\quad 1\\leq d\\lt 2^W,\\quad 0\\leq x\\lt 2^W$ において 除算の商 $\\left\\lfloor x/d\\right\\rfloor$ を計算:\n\n- $d=1$ の場合:\n    - $\\displaystyle\\left\\lfloor\\frac{x}{d}\\right\\rfloor=x$\n    - 擬似コード: `x`\n- $\\log_2d=\\lceil\\log_2d\\rceil$ ($d$ が $2$ の累乗数) の場合:\n    - $\\displaystyle t=\\log_2d,\\quad\\left\\lfloor\\frac{x}{d}\\right\\rfloor=\\left\\lfloor\\frac{x}{2^{\\log_2d}}\\right\\rfloor$\n    - 前計算: $s=\\log_2d$\n    - 擬似コード: `x >> s`\n- $\\displaystyle 2\\leq d\\lt 2^W,\\quad t=\\lfloor\\log_2(d-1)\\rfloor+W,\\quad\\left((-2^t)\\operatorname{mod}d\\right)x\\lt 2^t$ の場合:\n    - $0\\leq x\\lt 2^{W-1}\\quad\\longrightarrow\\quad\\left((-2^t)\\operatorname{mod}d\\right)x\\lt 2^t$\n    - $0\\leq x\\lt 2^W,\\quad (-2^t)\\operatorname{mod}d\\lt 2^{(t-W)}\\quad\\longrightarrow\\quad \\left((-2^t)\\operatorname{mod}d\\right)x\\lt 2^t$\n    - $\\displaystyle 2^{(t-W)}\\leq(d-1)\\lt d\\leq 2^{(t-W+1)},\\quad 2^{(W-1)}\\leq\\lceil 2^t/d\\rceil\\lt 2^W,\\quad 0\\leq t-W=\\lfloor\\log_2(d-1)\\rfloor\\lt W,$\n    - $\\displaystyle \\left\\lfloor\\frac{x}{d}\\right\\rfloor=\\left\\lfloor\\left\\lceil\\frac{2^t}{d}\\right\\rceil\\frac{x}{2^t}\\right\\rfloor=\\left\\lfloor\\left\\lfloor\\left\\lceil\\frac{2^t}{d}\\right\\rceil\\frac{x}{2^W}\\right\\rfloor\\frac{1}{2^{(t-W)}}\\right\\rfloor$\n    - 前計算: $\\displaystyle s=\\lfloor\\log_2(d-1)\\rfloor,\\quad t=s+W,\\quad m=\\left\\lceil 2^t/d\\right\\rceil$\n    - 擬似コード: `mulh(m, x) >> s`\n- $\\left(2\\leq d\\lt 2^W,\\quad 0\\leq x\\lt 2^W\\right)$ の範囲にて、主に上記以外の場合: \n    - $\\displaystyle t=\\lfloor\\log_2(d-1)\\rfloor+W+1,\\quad$\n    - $\\displaystyle 2^{(t-W-1)}\\leq(d-1)\\lt d\\leq 2^{(t-W)},\\quad 2^W\\leq\\lceil 2^t/d\\rceil\\lt 2^{(W+1)},\\quad$\n    - $\\displaystyle y=\\left\\lfloor\\left\\lceil\\frac{2^t}{d}\\right\\rceil\\frac{x}{2^W}\\right\\rfloor-x=\\left\\lfloor\\left(\\left\\lceil\\frac{2^t}{d}\\right\\rceil-2^W\\right)\\frac{x}{2^W}\\right\\rfloor,\\quad 0\\leq y\\leq x\\lt 2^W,\\quad$\n    - $\\displaystyle\\left\\lfloor\\frac{x}{d}\\right\\rfloor=\\left\\lfloor\\left\\lceil\\frac{2^t}{d}\\right\\rceil\\frac{x}{2^t}\\right\\rfloor=\\left\\lfloor\\frac{x+y}{2^{(t-W)}}\\right\\rfloor=\\left\\lfloor\\left(\\left\\lfloor\\frac{x-y}{2}\\right\\rfloor+y\\right)\\frac{1}{2^{(t-W-1)}}\\right\\rfloor$\n    - 前計算: $\\displaystyle s=\\lfloor\\log_2(d-1)\\rfloor,\\quad t=s+W+1,\\quad m=\\left\\lceil 2^t/d\\right\\rceil-2^W$\n    - 擬似コード: `y = mulh(m, x); (((x - y) >> 1) + y) >> s`\n\n#### 例\n\n$\\displaystyle x\\in\\mathbb{Z},\\quad 0\\leq x\\lt 2^{67}\\lt\\frac{2^{93}}{39898175}\\quad\\longrightarrow\\quad \\left\\lfloor\\left\\lceil\\frac{2^{93}}{998244353}\\right\\rceil\\times\\frac{x}{2^{93}}\\right\\rfloor=\\left\\lfloor\\frac{2^{93}+39898175}{998244353}\\times\\frac{x}{2^{93}}\\right\\rfloor=\\left\\lfloor\\frac{x}{998244353}\\right\\rfloor$\n\n$\\displaystyle x\\in\\mathbb{Z},\\quad 0\\le x\\lt 2^{70}\\lt\\frac{2^{90}}{875776}\\quad\\longrightarrow\\quad\\left\\lfloor\\left\\lceil\\frac{2^{90}}{10^8}\\right\\rceil\\times\\frac{x}{2^{90}}\\right\\rfloor=\\left\\lfloor\\frac{2^{90}+875776}{10^8}\\times\\frac{x}{2^{90}}\\right\\rfloor=\\left\\lfloor\\frac{x}{10^8}+\\frac{875776 x}{2^{90}\\times 10^8}\\right\\rfloor=\\left\\lfloor\\frac{x}{10^8}\\right\\rfloor$\n\n$\\displaystyle x\\in\\mathbb{Z},\\quad 0\\le x\\lt 10^{10}\\lt 2^{34}\\lt\\frac{2^{45}}{1168}\\quad\\longrightarrow\\quad\\left\\lfloor\\left\\lceil\\frac{2^{45}}{10^4}\\right\\rceil\\times\\frac{x}{2^{45}}\\right\\rfloor=\\left\\lfloor\\frac{2^{45}+1168}{10^4}\\times\\frac{x}{2^{45}}\\right\\rfloor=\\left\\lfloor\\frac{x}{10^4}+\\frac{1168 x}{2^{45}\\times 10^4}\\right\\rfloor=\\left\\lfloor\\frac{x}{10^4}\\right\\rfloor$\n\n$\\displaystyle x\\in\\mathbb{Z},\\quad 0\\le x\\lt 43690\\lt\\frac{2^{19}}{12}\\quad\\longrightarrow\\quad\\left\\lfloor\\left\\lceil\\frac{2^{19}}{10^2}\\right\\rceil\\times\\frac{x}{2^{19}}\\right\\rfloor=\\left\\lfloor\\frac{2^{19}+12}{10^2}\\times\\frac{x}{2^{19}}\\right\\rfloor=\\left\\lfloor\\frac{x}{10^2}+\\frac{12 x}{2^{19}\\times 10^2}\\right\\rfloor=\\left\\lfloor\\frac{x}{10^2}\\right\\rfloor$\n\n$\\displaystyle x\\in\\mathbb{Z},\\quad 0\\le x\\lt 1024=\\frac{2^{11}}{2}\\quad\\longrightarrow\\quad \\left\\lfloor\\left\\lceil\\frac{2^{11}}{10}\\right\\rceil\\times\\frac{x}{2^{11}}\\right\\rfloor=\\left\\lfloor\\frac{2^{11}+2}{10}\\times\\frac{x}{2^{11}}\\right\\rfloor=\\left\\lfloor\\frac{x}{10}+\\frac{2 x}{2^{11}\\times 10}\\right\\rfloor=\\left\\lfloor\\frac{x}{10}\\right\\rfloor$\n\n$\\displaystyle x\\in\\mathbb{Z},\\quad 0\\le x\\lt 2^{64}\\lt\\frac{2^{67}}{5}\\quad\\longrightarrow\\quad \\left\\lfloor\\left\\lceil\\frac{2^{67}}{7}\\right\\rceil\\times\\frac{x}{2^{67}}\\right\\rfloor=\\left\\lfloor\\frac{2^{67}+5}{7}\\times\\frac{x}{2^{67}}\\right\\rfloor=\\left\\lfloor\\frac{x}{7}+\\frac{5 x}{2^{67}\\times 7}\\right\\rfloor=\\left\\lfloor\\frac{x}{7}\\right\\rfloor$ $\\quad\\displaystyle\\left(2^{64}\\lt\\frac{2^{67}+5}{7}\\lt 2^{65}\\text{ である事に実装上注意}\\right)$\n\n### b. 丁度か $1$ 小さい値を求める ($d:$ 除数, $x:$ 被除数, $s,t:$ パラメータ [ $x$ の範囲に影響 ])\n\n$\\displaystyle d,s,t,x\\in\\mathbb{Z},\\quad 0\\le s,\\quad 0\\le t,\\quad 2^s\\le d\\le 2^{(s+t)},$\n\n$\\begin{cases}\\displaystyle\\left(\\left\\lfloor\\frac{x}{d}\\right\\rfloor-1\\right)\\le\\left\\lfloor\\left\\lfloor\\frac{x}{2^s}\\right\\rfloor\\left\\lfloor\\frac{2^{(s+t)}}{d}\\right\\rfloor\\frac{1}{2^t}\\right\\rfloor\\le\\left\\lfloor\\frac{x}{d}\\right\\rfloor\\\\ \\quad\\quad\\displaystyle\\left(0\\lt 2^{(s+t)}\\operatorname{mod}d\\lt d,\\quad 0\\le x\\lt \\frac{2^{(s+t)}(d-2^s+1)}{2^{(s+t)}\\operatorname{mod}d}+2^s-1\\right)\\\\\\displaystyle\\left\\lfloor\\frac{x}{d}\\right\\rfloor=\\left\\lfloor\\left\\lfloor\\frac{x}{2^s}\\right\\rfloor\\left\\lfloor\\frac{2^{(s+t)}}{d}\\right\\rfloor\\frac{1}{2^t}\\right\\rfloor\\\\ \\quad\\quad\\displaystyle\\left(2^{(s+t)}\\operatorname{mod}d=0,\\quad 0\\le x\\displaystyle\\right)\\end{cases}$\n\n- 前計算: $\\displaystyle m=\\left\\lfloor\\frac{2^{(s+t)}}{d}\\right\\rfloor$\n- 擬似コード: `((x >> s) * m) >> t`\n- $s=0$ の場合の擬似コード: `(m * x) >> t`\n- $s=0,t=W$ の場合の擬似コード: `mulh(m, x)` ※ $d=1$ の場合、 $m=\\lfloor 2^W/d\\rfloor=2^W$ となる事に注意\n\n#### 前半の導出\n\n$\\displaystyle d,s,t,x\\in\\mathbb{Z},\\quad 0\\le s,\\quad 0\\le t,\\quad 2^s\\le d\\le 2^{(s+t)},\\quad 0\\lt 2^{(s+t)}\\operatorname{mod}d\\lt d,\\quad 0\\le x\\lt \\frac{2^{(s+t)}(d-2^s+1)}{2^{(s+t)}\\operatorname{mod}d}+2^s-1$\n\n$\\displaystyle\\quad\\longrightarrow\\quad\\left(\\frac{\\left(2^s-1\\right)\\left(2^{(s+t)}-\\left(2^{(s+t)}\\operatorname{mod}d\\right)\\right)}{2^{(s+t)}d}-1\\right)\\lt\\left(-\\frac{2^{(s+t)}\\operatorname{mod}d}{2^{(s+t)}d}x\\right)\\leq 0 \\quad\\quad$ $\\displaystyle\\left(-\\frac{2^{(s+t)}\\operatorname{mod}d}{2^{(s+t)}d}\\text{ を掛ける}\\right)$\n\n$\\displaystyle\\quad\\longrightarrow\\quad\\left(\\frac{x}{d}-1\\right)\\lt\\left(\\frac{x-2^s+1}{2^s}\\left\\lfloor\\frac{2^{(s+t)}}{d}\\right\\rfloor\\frac{1}{2^t}\\right)=\\frac{\\left(x-2^s+1\\right)\\left(2^{(s+t)}-\\left(2^{(s+t)}\\operatorname{mod}d\\right)\\right)}{2^{(s+t)}d}\\leq\\left(\\frac{x}{d}-\\frac{2^s-1}{2^{(s+t)}}\\left\\lfloor\\frac{2^{(s+t)}}{d}\\right\\rfloor\\right)\\leq\\frac{x}{d}\\quad\\quad$ $\\displaystyle\\left(\\left(\\frac{x}{d}-\\frac{2^s-1}{2^{(s+t)}}\\left\\lfloor\\frac{2^{(s+t)}}{d}\\right\\rfloor\\right)=\\frac{2^{(s+t)}x-(2^s-1)\\left(2^{(s+t)}-\\left(2^{(s+t)}\\operatorname{mod}d\\right)\\right)}{2^{(s+t)}d}\\text{ を足す},\\ \\frac{2^{(s+t)}-\\left(2^{(s+t)}\\operatorname{mod}d\\right)}{d}=\\left\\lfloor\\frac{2^{(s+t)}}{d}\\right\\rfloor\\right)$\n\n$\\displaystyle\\quad\\longrightarrow\\quad \\left(\\frac{x}{d}-1\\right)\\lt\\left(\\frac{x-2^s+1}{2^s}\\left\\lfloor\\frac{2^{(s+t)}}{d}\\right\\rfloor\\frac{1}{2^t}\\right)\\le\\left(\\left\\lfloor\\frac{x}{2^s}\\right\\rfloor\\left\\lfloor\\frac{2^{(s+t)}}{d}\\right\\rfloor\\frac{1}{2^t}\\right)\\le\\frac{x}{d}\\quad\\quad$ $\\displaystyle\\left(\\frac{x}{2^s}-1\\lt\\frac{x-2^s+1}{2^s}\\le\\left\\lfloor\\frac{x}{2^s}\\right\\rfloor\\le\\frac{x}{2^s}\\right)$\n\n$\\displaystyle\\quad\\longrightarrow\\quad\\left(\\left\\lfloor\\frac{x}{d}\\right\\rfloor-1\\right)\\le\\left\\lfloor\\left\\lfloor\\frac{x}{2^s}\\right\\rfloor\\left\\lfloor\\frac{2^{(s+t)}}{d}\\right\\rfloor\\frac{1}{2^t}\\right\\rfloor\\le\\left\\lfloor\\frac{x}{d}\\right\\rfloor\\quad\\quad$ $\\left(\\text{床関数(floor)を適用}\\right)$\n\n\n#### 例\n\n$\\displaystyle x\\in\\mathbb{Z},\\quad 0\\leq x\\lt 2^{64}\\lt\\frac{2^{64}\\times 998244353}{2^{64}\\operatorname{mod}998244353}\\quad\\longrightarrow\\quad\\left\\lfloor\\frac{x}{998244353}\\right\\rfloor-1\\leq\\left\\lfloor\\left\\lfloor\\frac{2^{64}}{998244353}\\right\\rfloor\\times\\frac{x}{2^{64}}\\right\\rfloor=\\left\\lfloor\\frac{2^{64}-932051910}{998244353}\\times\\frac{x}{2^{64}}\\right\\rfloor\\leq\\left\\lfloor\\frac{x}{998244353}\\right\\rfloor$\n\n$\\displaystyle x\\in\\mathbb{Z},\\quad 0\\leq x\\lt 2^{128}\\displaystyle\\quad\\longrightarrow\\quad\\left(\\left\\lfloor\\frac{x}{10^{32}}\\right\\rfloor-1\\right)\\leq\\left\\lfloor\\left\\lfloor\\frac{x}{2^{64}}\\right\\rfloor\\times\\left\\lfloor\\frac{2^{128}}{10^{32}}\\right\\rfloor\\times\\frac{1}{2^{64}}\\right\\rfloor\\leq\\left\\lfloor\\frac{x}{10^{32}}\\right\\rfloor$\n\n$\\displaystyle x\\in\\mathbb{Z},\\quad 0\\leq x\\lt 10^{32}\\displaystyle\\quad\\longrightarrow\\quad\\begin{cases}\\displaystyle\\left(\\left\\lfloor\\frac{x}{10^{16}}\\right\\rfloor-1\\right)\\leq\\left\\lfloor\\left\\lfloor\\frac{x}{2^{43}}\\right\\rfloor\\times\\left\\lfloor\\frac{2^{107}}{10^{16}}\\right\\rfloor\\times\\frac{1}{2^{64}}\\right\\rfloor\\leq\\left\\lfloor\\frac{x}{10^{16}}\\right\\rfloor\\\\\\displaystyle\\left(\\left\\lfloor\\frac{x}{10^{16}}\\right\\rfloor-1\\right)\\leq\\left\\lfloor\\left\\lfloor\\frac{x}{2^{48}}\\right\\rfloor\\times\\left\\lfloor\\frac{2^{112}}{10^{16}}\\right\\rfloor\\times\\frac{1}{2^{64}}\\right\\rfloor\\leq\\left\\lfloor\\frac{x}{10^{16}}\\right\\rfloor\\\\\\displaystyle\\left(\\left\\lfloor\\frac{x}{10^{16}}\\right\\rfloor-1\\right)\\leq\\left\\lfloor\\left\\lfloor\\frac{x}{2^{52}}\\right\\rfloor\\times\\left\\lfloor\\frac{2^{116}}{10^{16}}\\right\\rfloor\\times\\frac{1}{2^{64}}\\right\\rfloor\\leq\\left\\lfloor\\frac{x}{10^{16}}\\right\\rfloor\\end{cases}$\n\n\n### c. 丁度か $1$ 大きい値を求める ($d:$ 除数, $x:$ 被除数, $s,t:$ パラメータ [ $x$ の範囲に影響 ])\n\n$\\displaystyle d,s,t,x\\in\\mathbb{Z},\\quad 0\\le s,\\quad 0\\le t,\\quad 2^s\\le d\\le 2^{(s+t)},$\n\n$\\begin{cases}\\displaystyle\\left\\lfloor\\frac{x}{d}\\right\\rfloor\\le\\left\\lfloor\\left\\lceil\\frac{x}{2^s}\\right\\rceil\\left\\lceil\\frac{2^{(s+t)}}{d}\\right\\rceil\\frac{1}{2^t}\\right\\rfloor\\le\\left(\\left\\lfloor\\frac{x}{d}\\right\\rfloor+1\\right)\\\\ \\quad\\quad\\displaystyle\\left(0\\lt\\left(-2^{(s+t)}\\right)\\operatorname{mod}d\\lt d,\\quad 0\\le x\\lt \\frac{2^{(s+t)}(d-2^s+1)}{\\left(-2^{(s+t)}\\right)\\operatorname{mod}d}-2^s+1\\right)\\\\ \\displaystyle\\left\\lfloor\\frac{x}{d}\\right\\rfloor\\le\\left\\lfloor\\left\\lceil\\frac{x}{2^s}\\right\\rceil\\left\\lceil\\frac{2^{(s+t)}}{d}\\right\\rceil\\frac{1}{2^t}\\right\\rfloor\\le\\left(\\left\\lfloor\\frac{x}{d}\\right\\rfloor+1\\right)\\\\ \\quad\\quad\\displaystyle\\left(\\left(-2^{(s+t)}\\right)\\operatorname{mod}d=0,\\quad 0\\le x\\right)\\end{cases}$\n\n- 前計算: $\\displaystyle u=2^s-1,\\quad m=\\left\\lceil\\frac{2^{(s+t)}}{d}\\right\\rceil$\n- 擬似コード: `(((x + u) >> s) * m) >> t`\n- $s=0$ の場合の擬似コード: `(x * m) >> t`\n- $s=0, t=W$ の場合の擬似コード: `mulh(m, x)` ※ $d=1$ の場合、 $m=\\lceil 2^W/d\\rceil=2^W$ となる事に注意\n\n$s=0$ の場合のみの実用を想定。 ($s\\gt 0$ だと b. の手法に比べて利点が薄いため)\n\n$s=0, t=W=64$ の場合の利用例: ac-library の barrett reduction 実装における、除算の商の近似値を求める部分\n\n$1\\leq d\\lt 2^{64}:\\text{ 除数},\\quad 0\\leq x\\lt 2^{64}:\\text{ 被除数}$ $\\displaystyle\\quad\\longrightarrow\\quad\\left\\lfloor\\frac{x}{d}\\right\\rfloor\\leq\\left\\lfloor\\left\\lceil\\frac{2^{64}}{d}\\right\\rceil\\frac{x}{2^{64}}\\right\\rfloor\\leq\\left\\lfloor\\frac{x}{d}\\right\\rfloor+1$\n\nhttps://github.com/atcoder/ac-library/blob/master/atcoder/internal_math.hpp#L51-L59\n\n#### 前半の導出\n\n$\\displaystyle d,s,t,x\\in\\mathbb{Z},\\quad 0\\le s,\\quad 0\\le t,\\quad 2^s\\le d\\le 2^{(s+t)},\\quad 0\\lt\\left(-2^{(s+t)}\\right)\\operatorname{mod}d\\lt d,\\quad 0\\le x\\lt \\frac{2^{(s+t)}(d-2^s+1)}{\\left(-2^{(s+t)}\\right)\\operatorname{mod}d}-2^s+1$\n\n$\\displaystyle\\quad\\longrightarrow\\quad 0\\leq \\frac{\\left(-2^{(s+t)}\\right)\\operatorname{mod}d}{2^{(s+t)}d}x\\lt \\left(1-\\frac{(2^s-1)\\left(2^{(s+t)}+\\left(\\left(-2^{(s+t)}\\right)\\operatorname{mod}d\\right)\\right)}{2^{(s+t)}d}\\right) \\quad\\quad$ $\\displaystyle\\left(\\frac{\\left(-2^{(s+t)}\\right)\\operatorname{mod}d}{2^{(s+t)}d}\\text{ を掛ける}\\right)$\n\n$\\displaystyle\\quad\\longrightarrow\\quad\\frac{x}{d}\\leq\\left(\\frac{x}{d}+\\frac{2^s-1}{2^{(s+t)}}\\left\\lceil\\frac{2^{(s+t)}}{d}\\right\\rceil\\right)\\leq\\left(\\frac{x+2^s-1}{2^s}\\left\\lceil\\frac{2^{(s+t)}}{d}\\right\\rceil\\frac{1}{2^t}\\right)=\\frac{\\left(x+2^s-1\\right)\\left(2^{(s+t)}+\\left(\\left(-2^{(s+t)}\\right)\\operatorname{mod}d\\right)\\right)}{2^{(s+t)}d}\\lt\\left(\\frac{x}{d}+1\\right)$\n$\\displaystyle\\left(\\left(\\frac{x}{d}+\\frac{2^s-1}{2^{(s+t)}}\\left\\lceil\\frac{2^{(s+t)}}{d}\\right\\rceil\\right)=\\frac{2^{(s+t)}x+(2^s-1)\\left(2^{(s+t)}+\\left(\\left(-2^{(s+t)}\\right)\\operatorname{mod}d\\right)\\right)}{2^{(s+t)}d}\\text{ を足す},\\ \\frac{2^{(s+t)}+\\left(\\left(-2^{(s+t)}\\right)\\operatorname{mod}d\\right)}{d}=\\left\\lceil\\frac{2^{(s+t)}}{d}\\right\\rceil\\right)$\n\n$\\displaystyle\\quad\\longrightarrow\\quad\\frac{x}{d}\\leq\\left(\\left\\lceil\\frac{x}{2^s}\\right\\rceil\\left\\lceil\\frac{2^{(s+t)}}{d}\\right\\rceil\\frac{1}{2^t}\\right)\\leq\\left(\\frac{x+2^s-1}{2^s}\\left\\lceil\\frac{2^{(s+t)}}{d}\\right\\rceil\\frac{1}{2^t}\\right)\\lt\\left(\\frac{x}{d}+1\\right)\\quad\\quad$ $\\displaystyle\\left(\\frac{x}{2^s}\\leq\\left\\lceil\\frac{x}{2^s}\\right\\rceil\\leq\\frac{x+2^s-1}{2^s}\\lt\\frac{x}{2^s}+1\\right)$\n\n$\\displaystyle\\quad\\longrightarrow\\quad\\left\\lfloor\\frac{x}{d}\\right\\rfloor\\le\\left\\lfloor\\left\\lceil\\frac{x}{2^s}\\right\\rceil\\left\\lceil\\frac{2^{(s+t)}}{d}\\right\\rceil\\frac{1}{2^t}\\right\\rfloor\\le\\left(\\left\\lfloor\\frac{x}{d}\\right\\rfloor+1\\right)\\quad\\quad$ $\\left(\\text{床関数(floor)を適用}\\right)$\n\n#### 例\n\n$\\displaystyle x\\in\\mathbb{Z},\\quad 0\\leq x\\lt 2^{67}\\lt\\frac{2^{64}\\times 998244353}{(-2^{64})\\operatorname{mod}998244353}\\quad\\longrightarrow\\quad\\left\\lfloor\\frac{x}{998244353}\\right\\rfloor\\leq\\left\\lfloor\\left\\lceil\\frac{2^{64}}{998244353}\\right\\rceil\\times\\frac{x}{2^{64}}\\right\\rfloor=\\left\\lfloor\\frac{2^{64}+66192443}{998244353}\\times\\frac{x}{2^{64}}\\right\\rfloor\\leq\\left\\lfloor\\frac{x}{998244353}\\right\\rfloor+1$\n",
      "body_updated_at": "2023-08-09"
    }
  ]
}